xiaothink/__init__.py
xiaothink/llm/__init__.py
xiaothink/llm/img_zip/__init__.py
xiaothink/llm/img_zip/img_zip.py
xiaothink/llm/inference/__init__.py
xiaothink/llm/inference/build_model.py
xiaothink/llm/inference/test.py
xiaothink/llm/inference/test_formal.py
xiaothink/llm/inference/test_vision.py
xiaothink/llm/inference/vision_api.py
xiaothink-1.3.2.dist-info/LICENSE
xiaothink-1.3.2.dist-info/METADATA
xiaothink-1.3.2.dist-info/NOTICE
xiaothink-1.3.2.dist-info/WHEEL
xiaothink-1.3.2.dist-info/top_level.txt
xiaothink-1.3.2.dist-info/RECORD
