Metadata-Version: 2.1
Name: xiaothink
Version: 1.3.2
Summary: An AI toolkit that helps users quickly call interfaces related to the Xiaothink framework.
Author: Shi Jingqi
Author-email: xiaothink@foxmail.com
License: Apache License 2.0
Classifier: Development Status :: 4 - Beta
Classifier: Intended Audience :: Developers
Classifier: Intended Audience :: Science/Research
Classifier: License :: OSI Approved :: Apache Software License
Classifier: Programming Language :: Python :: 3
Classifier: Programming Language :: Python :: 3.8
Classifier: Programming Language :: Python :: 3.9
Classifier: Programming Language :: Python :: 3.10
Classifier: Programming Language :: Python :: 3.11
Classifier: Topic :: Scientific/Engineering :: Artificial Intelligence
Classifier: Operating System :: OS Independent
Requires-Python: >=3
License-File: LICENSE
License-File: NOTICE
Requires-Dist: numpy (>=1.21.0)
Requires-Dist: tensorflow (>=2.10.0)
